Metadata-Version: 2.1
Name: graph-read-simulator
Version: 0.0.20
Summary: Graph Read Simulator
Home-page: http://github.com/ivargr/graph_read_simulator
Author: Ivar Grytten
Author-email: 
License: MIT
Classifier: Programming Language :: Python :: 3
